taxonomy/TODO
taxonomy/__init__.py
taxonomy/admins.py
taxonomy/api.py
taxonomy/apps.py
taxonomy/forms.py
taxonomy/inline_templates.py
taxonomy/models.py
taxonomy/templates/taxonomy/term_change_form.html
taxonomy/templates/taxonomy/term_change_list.html
taxonomy/templatetags/taxonomy_displays.py
taxonomy/ttest/apps.py
taxonomy/ttest/models.py
taxonomy/ttest/migrations/0001_initial.py
taxonomy/ttest/migrations/__init__.py
taxonomy/ttest/tests/test_api.py
taxonomy/ttest/tests/test_models.py
taxonomy/ttest/tests/utils.py
django_taxonomy2-1.1.1.dist-info/LICENSE
django_taxonomy2-1.1.1.dist-info/WHEEL
django_taxonomy2-1.1.1.dist-info/METADATA
django_taxonomy2-1.1.1.dist-info/RECORD
