Metadata-Version: 2.1
Name: django-taxonomy2
Version: 1.1.1
Summary: Category tree for Django. Replicable and customizable. Includes Admin. Low on features, easy setup.
Home-page: https://github.com/rcrowther/django-taxonomy
Author: robert crowther
Author-email: rw.crowther@gmail.com
Classifier: Operating System :: OS Independent
Classifier: License :: OSI Approved :: BSD License
Classifier: Programming Language :: Python :: 3
Classifier: Framework :: Django
